testmayathing/__init__.py
testmayathing/testmayathing.py
test_maya_thing-0.3.0.dist-info/LICENSE
test_maya_thing-0.3.0.dist-info/WHEEL
test_maya_thing-0.3.0.dist-info/METADATA
test_maya_thing-0.3.0.dist-info/RECORD
