Metadata-Version: 2.1
Name: test-maya-thing
Version: 0.3.0
Summary: Maya Boilerplate contains all the boilerplate you need to create a Maya Python package.
License: MIT
Author: Mitchell Coote
Author-email: mitchellcoote@gmail.com
Requires-Python: >=2.7, !=3.0.*, !=3.1.*, !=3.2.*, !=3.3.*
Classifier: License :: OSI Approved :: MIT License
Classifier: Programming Language :: Python :: 2
Classifier: Programming Language :: Python :: 3
Classifier: Programming Language :: Python :: 3.4
Classifier: Programming Language :: Python :: 3.5
Classifier: Programming Language :: Python :: 3.6
Classifier: Programming Language :: Python :: 3.7
